instackup/__init__.py
instackup/bigquery_tools.py
instackup/gcloudstorage_tools.py
instackup/general_tools.py
instackup/gsheets_tools.py
instackup/heroku_tools.py
instackup/redshift_tools.py
instackup/s3_tools.py
instackup/sql_tools.py
test/__init__.py
test/test_general_tools.py
instackup-0.3.0.dist-info/LICENSE
instackup-0.3.0.dist-info/METADATA
instackup-0.3.0.dist-info/WHEEL
instackup-0.3.0.dist-info/top_level.txt
instackup-0.3.0.dist-info/RECORD
