Metadata-Version: 2.1
Name: instackup
Version: 0.3.0
Summary: A package to ease interaction with cloud services, DB connections and commonly used functionalities in data analytics.
Home-page: https://github.com/Lavedonio/instackup
Author: Daniel Lavedonio de Lima
Author-email: daniel.lavedonio@gmail.com
License: MIT
Platform: any
Classifier: Programming Language :: Python :: 3
Classifier: License :: OSI Approved :: MIT License
Classifier: Operating System :: OS Independent
Requires-Python: >=3.6
Requires-Dist: PyYAML (>=5.1)
Requires-Dist: boto3 (>=1.14.0)
Requires-Dist: google-cloud-bigquery (>=1.26.0)
Requires-Dist: google-cloud-bigquery-datatransfer (>=1.1.0)
Requires-Dist: google-cloud-storage (>=1.18.0)
Requires-Dist: grpcio (==1.34.0)
Requires-Dist: gcsfs (==0.7.1)
Requires-Dist: gspread (==3.6.0)
Requires-Dist: mysql-connector-python (>=8.0.21)
Requires-Dist: pandas (>=1.1.0)
Requires-Dist: pandas-gbq (>=0.14.0)
Requires-Dist: psycopg2-binary (==2.8.6)
